codexp/README.md
codexp/__init__.py
codexp/__main__.py
codexp/analyzer.py
codexp/import_visitor.py
codexp/symbol_usage_visitor.py
codexp/symbol_visitor.py
codexp/visterm.py
codexp/codexp/analyzer.py
codexp/codexp/import_visitor.py
codexp-0.1.0.dist-info/METADATA
codexp-0.1.0.dist-info/WHEEL
codexp-0.1.0.dist-info/entry_points.txt
codexp-0.1.0.dist-info/licenses/LICENSE
codexp-0.1.0.dist-info/RECORD
