Metadata-Version: 2.4
Name: codexp
Version: 0.1.0
Summary: A CLI tool to analyze Python packages and visualize their structure and dependencies
Project-URL: Homepage, https://github.com/yourusername/codexp
Project-URL: Repository, https://github.com/yourusername/codexp.git
Author-email: Your Name <your.email@example.com>
License: MIT
License-File: LICENSE
Classifier: Development Status :: 3 - Alpha
Classifier: Environment :: Console
Classifier: Intended Audience :: Developers
Classifier: License :: OSI Approved :: MIT License
Classifier: Programming Language :: Python :: 3.8
Classifier: Programming Language :: Python :: 3.9
Classifier: Programming Language :: Python :: 3.10
Classifier: Topic :: Software Development :: Documentation
Classifier: Topic :: Software Development :: Libraries :: Python Modules
Requires-Python: >=3.8
Requires-Dist: rich
Requires-Dist: typer
